{
  "$schema": "https://raw.githubusercontent.com/spdx/spdx-spec/v2.2.1/schemas/spdx-schema.json",
  "spdxVersion": "SPDX-2.2",
  "dataLicense": "CC0-1.0",
  "SPDXID": "SPDXRef-DOCUMENT",
  "documentNamespace": "https://spdx.org/spdxdocs/fmt-arm64-windows-static-5.3.0-1-f6b83a57-c5fe-4866-82f2-13ebaf63de94",
  "name": "fmt:arm64-windows-static@5.3.0-1 0bcfa211a2147da587f583608099d11daee96475032023c1d67c79d9b64d24b3",
  "creationInfo": {
    "creators": [
      "Tool: vcpkg-105f7f7e8a5ea10dfac9874ff9d1a6bacba5f454"
    ],
    "created": "2023-03-16T14:17:00Z"
  },
  "relationships": [
    {
      "spdxElementId": "SPDXRef-port",
      "relationshipType": "GENERATES",
      "relatedSpdxElement": "SPDXRef-binary"
    },
    {
      "spdxElementId": "SPDXRef-port",
      "relationshipType": "CONTAINS",
      "relatedSpdxElement": "SPDXRef-file-0"
    },
    {
      "spdxElementId": "SPDXRef-port",
      "relationshipType": "CONTAINS",
      "relatedSpdxElement": "SPDXRef-file-1"
    },
    {
      "spdxElementId": "SPDXRef-binary",
      "relationshipType": "GENERATED_FROM",
      "relatedSpdxElement": "SPDXRef-port"
    },
    {
      "spdxElementId": "SPDXRef-file-0",
      "relationshipType": "CONTAINED_BY",
      "relatedSpdxElement": "SPDXRef-port"
    },
    {
      "spdxElementId": "SPDXRef-file-1",
      "relationshipType": "CONTAINED_BY",
      "relatedSpdxElement": "SPDXRef-port"
    }
  ],
  "packages": [
    {
      "name": "fmt",
      "SPDXID": "SPDXRef-port",
      "versionInfo": "5.3.0-1",
      "downloadLocation": "git+https://github.com/Microsoft/vcpkg@14ae41740d43442b12f3be229232698dd10b33d5",
      "licenseConcluded": "NOASSERTION",
      "licenseDeclared": "NOASSERTION",
      "copyrightText": "NOASSERTION",
      "description": "Formatting library for C++. It can be used as a safe alternative to printf or as a fast alternative to IOStreams.",
      "comment": "This is the port (recipe) consumed by vcpkg."
    },
    {
      "name": "fmt:arm64-windows-static",
      "SPDXID": "SPDXRef-binary",
      "versionInfo": "0bcfa211a2147da587f583608099d11daee96475032023c1d67c79d9b64d24b3",
      "downloadLocation": "NONE",
      "licenseConcluded": "NOASSERTION",
      "licenseDeclared": "NOASSERTION",
      "copyrightText": "NOASSERTION",
      "comment": "This is a binary package built by vcpkg."
    },
    {
      "SPDXID": "SPDXRef-resource-1",
      "name": "fmtlib/fmt",
      "downloadLocation": "git+https://github.com/fmtlib/fmt@5.3.0",
      "licenseConcluded": "NOASSERTION",
      "licenseDeclared": "NOASSERTION",
      "copyrightText": "NOASSERTION",
      "checksums": [
        {
          "algorithm": "SHA512",
          "checksumValue": "9ef0f3d328681253c1e1776576d54d67dec49c19fd7fc422ae63c3610b01a3f05f6e83cdf5e913dfd09bac42e52fe35c38ebe1ea91f4207d226a32aaf69eb4a8"
        }
      ]
    }
  ],
  "files": [
    {
      "fileName": "./CONTROL",
      "SPDXID": "SPDXRef-file-0",
      "checksums": [
        {
          "algorithm": "SHA256",
          "checksumValue": "911d6881b61518f3e61e109457dfe6a41cf6cdb13b42aa04f2da5900144fcdf6"
        }
      ],
      "licenseConcluded": "NOASSERTION",
      "copyrightText": "NOASSERTION"
    },
    {
      "fileName": "./portfile.cmake",
      "SPDXID": "SPDXRef-file-1",
      "checksums": [
        {
          "algorithm": "SHA256",
          "checksumValue": "a60176c265d008a6f60c647a631666448f314166304f6346702432309ae124fd"
        }
      ],
      "licenseConcluded": "NOASSERTION",
      "copyrightText": "NOASSERTION"
    }
  ]
}
